common_helper/__init__.py
common_helper/json_helper.py
common_helper/jwt_helper.py
common_helper/otp_helper.py
common_helper/patch.py
common_helper/request_validator.py
common_helper/request_validator_example.py
myvenv/Lib/site-packages/blinker/__init__.py
myvenv/Lib/site-packages/blinker/_utilities.py
myvenv/Lib/site-packages/blinker/base.py
myvenv/Lib/site-packages/blinker/py.typed
myvenv/Lib/site-packages/build/__init__.py
myvenv/Lib/site-packages/build/__main__.py
myvenv/Lib/site-packages/build/_builder.py
myvenv/Lib/site-packages/build/_ctx.py
myvenv/Lib/site-packages/build/_exceptions.py
myvenv/Lib/site-packages/build/_types.py
myvenv/Lib/site-packages/build/_util.py
myvenv/Lib/site-packages/build/env.py
myvenv/Lib/site-packages/build/py.typed
myvenv/Lib/site-packages/build/util.py
myvenv/Lib/site-packages/build/_compat/__init__.py
myvenv/Lib/site-packages/build/_compat/importlib.py
myvenv/Lib/site-packages/build/_compat/tarfile.py
myvenv/Lib/site-packages/build/_compat/tomllib.py
myvenv/Lib/site-packages/certifi/__init__.py
myvenv/Lib/site-packages/certifi/__main__.py
myvenv/Lib/site-packages/certifi/core.py
myvenv/Lib/site-packages/certifi/py.typed
myvenv/Lib/site-packages/charset_normalizer/__init__.py
myvenv/Lib/site-packages/charset_normalizer/__main__.py
myvenv/Lib/site-packages/charset_normalizer/api.py
myvenv/Lib/site-packages/charset_normalizer/cd.py
myvenv/Lib/site-packages/charset_normalizer/constant.py
myvenv/Lib/site-packages/charset_normalizer/legacy.py
myvenv/Lib/site-packages/charset_normalizer/md.py
myvenv/Lib/site-packages/charset_normalizer/models.py
myvenv/Lib/site-packages/charset_normalizer/py.typed
myvenv/Lib/site-packages/charset_normalizer/utils.py
myvenv/Lib/site-packages/charset_normalizer/version.py
myvenv/Lib/site-packages/charset_normalizer/cli/__init__.py
myvenv/Lib/site-packages/charset_normalizer/cli/__main__.py
myvenv/Lib/site-packages/click/__init__.py
myvenv/Lib/site-packages/click/_compat.py
sagarcustompackage-0.1.8.dist-info/METADATA
sagarcustompackage-0.1.8.dist-info/WHEEL
sagarcustompackage-0.1.8.dist-info/top_level.txt
sagarcustompackage-0.1.8.dist-info/RECORD
