Metadata-Version: 2.4
Name: sagarcustompackage
Version: 0.1.8
Summary: Reusable helpers for OTP, JWT authentication, JSON serialization, Flask request validator, and TLSv1.2 patch for Python requests.
Author-email: Sagar Sonara <sagarsonara2143@gmail.com>
License-Expression: MIT
Project-URL: Homepage, https://github.com/Sagarsonara2143/PyPi_CustomPackage
Requires-Python: >=3.8
Requires-Dist: pyjwt>=2.0.0
Requires-Dist: requests>=2.25.0
Requires-Dist: urllib3>=2.0.0
Requires-Dist: flask>=2.3.0
